Metadata-Version: 2.1
Name: odoo11-addon-account-mass-reconcile-transaction-ref
Version: 11.0.1.0.1
Summary: Mass Reconcile Transaction Ref
Home-page: https://github.com/OCA/account-reconcile
Author: Camptocamp,Odoo Community Association (OCA)
Author-email: support@odoo-community.org
License: AGPL-3
Platform: UNKNOWN
Classifier: Programming Language :: Python
Classifier: Framework :: Odoo
Classifier: License :: OSI Approved :: GNU Affero General Public License v3
Requires-Python: >=2.7, !=3.0.*, !=3.1.*, !=3.2.*, !=3.3.*, !=3.4.*
Requires-Dist: odoo11-addon-account-mass-reconcile
Requires-Dist: odoo11-addon-base-transaction-id
Requires-Dist: odoo (<11.1dev,>=11.0a)
